sse_bsa/__init__.py
sse_bsa/bsa_archive.py
sse_bsa/datatypes.py
sse_bsa/file_name_block.py
sse_bsa/file_record.py
sse_bsa/file_record_block.py
sse_bsa/folder_record.py
sse_bsa/header.py
sse_bsa/utilities.py
sse_bsa-1.1.0.dist-info/licenses/LICENSE
sse_bsa-1.1.0.dist-info/METADATA
sse_bsa-1.1.0.dist-info/WHEEL
sse_bsa-1.1.0.dist-info/top_level.txt
sse_bsa-1.1.0.dist-info/RECORD
