Metadata-Version: 2.4
Name: sse_bsa
Version: 1.1.0
Summary: A Python library to read and write BSA (archive) files for Skyrim Special Edition.
Author-email: Cutleast <cutleast@gmail.com>
License: MIT License
Project-URL: Homepage, https://github.com/cutleast/sse-bsa
Project-URL: Issues, https://github.com/cutleast/sse-bsa/issues
Classifier: Programming Language :: Python :: 3
Classifier: Operating System :: OS Independent
Requires-Python: >=3.12
License-File: LICENSE
Requires-Dist: lz4
Requires-Dist: virtual_glob
Dynamic: license-file
